{"status": 0, "statusText": "dailysentence", "dailysentence": [{"id": "2020-05-11 00:24:00", "en": "No matter how dark the moment, love and hope are always possible.", "cn": "\u65e0\u8bba\u773c\u524d\u6709\u591a\u9ed1\u6697\uff0c\u7231\u548c\u5e0c\u671b\u603b\u6709\u53ef\u80fd\u3002"}, {"id": "2020-05-11 00:26:00", "en": "No matter how dark the moment, love and hope are always possible.", "cn": "\u65e0\u8bba\u773c\u524d\u6709\u591a\u9ed1\u6697\uff0c\u7231\u548c\u5e0c\u671b\u603b\u6709\u53ef\u80fd\u3002"}, {"id": "2020-05-11 00:28:00", "en": "No matter how dark the moment, love and hope are always possible.", "cn": "\u65e0\u8bba\u773c\u524d\u6709\u591a\u9ed1\u6697\uff0c\u7231\u548c\u5e0c\u671b\u603b\u6709\u53ef\u80fd\u3002"}, {"id": "2020-05-11 00:30:00", "en": "No matter how dark the moment, love and hope are always possible.", "cn": "\u65e0\u8bba\u773c\u524d\u6709\u591a\u9ed1\u6697\uff0c\u7231\u548c\u5e0c\u671b\u603b\u6709\u53ef\u80fd\u3002"}, {"id": "2020-05-11 00:32:00", "en": "No matter how dark the moment, love and hope are always possible.", "cn": "\u65e0\u8bba\u773c\u524d\u6709\u591a\u9ed1\u6697\uff0c\u7231\u548c\u5e0c\u671b\u603b\u6709\u53ef\u80fd\u3002"}, {"id": "2020-05-11 00:34:00", "en": "No matter how dark the moment, love and hope are always possible.", "cn": "\u65e0\u8bba\u773c\u524d\u6709\u591a\u9ed1\u6697\uff0c\u7231\u548c\u5e0c\u671b\u603b\u6709\u53ef\u80fd\u3002"}, {"id": "2020-05-11 00:36:00", "en": "No matter how dark the moment, love and hope are always possible.", "cn": "\u65e0\u8bba\u773c\u524d\u6709\u591a\u9ed1\u6697\uff0c\u7231\u548c\u5e0c\u671b\u603b\u6709\u53ef\u80fd\u3002"}, {"id": "2020-05-11 00:38:00", "en": "No matter how dark the moment, love and hope are always possible.", "cn": "\u65e0\u8bba\u773c\u524d\u6709\u591a\u9ed1\u6697\uff0c\u7231\u548c\u5e0c\u671b\u603b\u6709\u53ef\u80fd\u3002"}, {"id": "2020-05-11 00:40:00", "en": "No matter how dark the moment, love and hope are always possible.", "cn": "\u65e0\u8bba\u773c\u524d\u6709\u591a\u9ed1\u6697\uff0c\u7231\u548c\u5e0c\u671b\u603b\u6709\u53ef\u80fd\u3002"}, {"id": "2020-05-11 00:42:00", "en": "No matter how dark the moment, love and hope are always possible.", "cn": "\u65e0\u8bba\u773c\u524d\u6709\u591a\u9ed1\u6697\uff0c\u7231\u548c\u5e0c\u671b\u603b\u6709\u53ef\u80fd\u3002"}, {"id": "2020-05-11 00:44:00", "en": "No matter how dark the moment, love and hope are always possible.", "cn": "\u65e0\u8bba\u773c\u524d\u6709\u591a\u9ed1\u6697\uff0c\u7231\u548c\u5e0c\u671b\u603b\u6709\u53ef\u80fd\u3002"}]}